cq/__init__.py
cq/checker.py
cq/checkers/__init__.py
cq/checkers/git.py
cq/checkers/init.py
cq/checkers/isort.py
cq/checkers/isort_config.py
cq/checkers/mypy.py
cq/checkers/orange.py
cq/checkers/pyflakes.py
cq/checkers/pylint.py
cq/checkers/pylintrc
cq/checkers/regex.py
cq/checkers/ruff.py
cq/checkers/safety.py
cq/checkers/setup.py
cq/checkers/test/data/formatted.txt
cq/checkers/test/data/isort.txt
cq/checkers/test/data/not-formatted.txt
cq/checkers/test/test_git.py
cq/checkers/test/test_init.py
cq/checkers/test/test_isort.py
cq/checkers/test/test_mypy.py
cq/checkers/test/test_orange.py
cq/checkers/test/test_pyflakes.py
cq/checkers/test/test_pylint.py
cq/checkers/test/test_regex.py
cq/checkers/test/test_ruff.py
cq/checkers/test/test_safety.py
cq/fixer.py
cq/fixers/__init__.py
cq/fixers/isort_fixer.py
cq/fixers/orange.py
cq/fixers/test/data/isort-result.txt
cq/fixers/test/data/isort-test.txt
cq/fixers/test/data/orange-result.txt
cq/fixers/test/data/orange-test.txt
cq/fixers/test/test_isort_fixer.py
cq/fixers/test/test_orange_fixer.py
cq/main.py
cq/test/test_cq.py
cq/test/test_utils.py
cq/utils.py
ql_cq-1.9.0.dist-info/LICENSE.txt
ql_cq-1.9.0.dist-info/METADATA
ql_cq-1.9.0.dist-info/WHEEL
ql_cq-1.9.0.dist-info/entry_points.txt
ql_cq-1.9.0.dist-info/RECORD
