Metadata-Version: 2.1
Name: ql-cq
Version: 1.9.0
Summary: Code quality checker
Home-page: https://gitlab.com/quantlane/meta/cq
License: Apache License, Version 2.0
Author: Quantlane
Author-email: code@quantlane.com
Requires-Python: >=3.10,<4.0
Classifier: License :: Other/Proprietary License
Classifier: Programming Language :: Python :: 3
Classifier: Programming Language :: Python :: 3.10
Classifier: Programming Language :: Python :: 3.11
Classifier: Programming Language :: Python :: 3.12
Requires-Dist: astpath[xpath] (>=0.6.1,<0.7.0)
Requires-Dist: click (>=3.0,<9.0)
Requires-Dist: isort (>=5.12.0,<6.0.0)
Requires-Dist: mypy (>=1.7.1,<2.0.0)
Requires-Dist: pyflakes (>=2.5.0,<3.0.0)
Requires-Dist: pyflakes-ext (>=2.0.0,<3.0.0)
Requires-Dist: pylint (>=3.0.2,<4.0.0)
Requires-Dist: ql-orange (>=1.1.0,<2.0.0)
Requires-Dist: requirements-parser (>=0.1.0,<1.0.0)
Requires-Dist: ruff (>=0.3.0,<0.4.0)
Requires-Dist: safety (>=2.3.5,<3.0.0,!=2.4.0b1,!=2.4.0b2,!=2.4.0b3)
Requires-Dist: setuptools (>=68.0.0)
Requires-Dist: toolz (>=0.8.2,<1.0.0)
